setup.py
mousepy/__init__.py
mousepy.egg-info/PKG-INFO
mousepy.egg-info/SOURCES.txt
mousepy.egg-info/dependency_links.txt
mousepy.egg-info/requires.txt
mousepy.egg-info/top_level.txt
mousepy/api/__init__.py
mousepy/api/heatmaps.py
mousepy/api/website.py
mousepy/api/websites.py
mousepy/api/recordings/__init__.py
mousepy/api/recordings/recording.py
mousepy/api/recordings/properties/__init__.py
mousepy/api/recordings/properties/bulktag.py
mousepy/api/recordings/properties/star.py
mousepy/api/recordings/properties/tag.py
mousepy/api/recordings/properties/tags.py
mousepy/api/recordings/properties/variables.py