Metadata-Version: 1.1
Name: mousepy
Version: 0.0.9
Summary: A wrapper for the Mouseflow API.
Home-page: https://github.com/newcraftgroup/mousepy
Author: NEWCRAFT
Author-email: admin.tech@newcraftgroup.com
License: Apache 2.0
Download-URL: https://github.com/newcraftgroup/mousepy/archive/v0.0.9.tar.gz
Keywords: api,wrapper,mouseflow,analytics,data
Platform: UNKNOWN
Classifier: Development Status :: 3 - Alpha
Classifier: Intended Audience :: Developers
Classifier: License :: OSI Approved :: Apache Software License
Classifier: Operating System :: OS Independent
Classifier: Programming Language :: Python
Classifier: Programming Language :: Python :: 3.6
Classifier: Topic :: Scientific/Engineering :: Information Analysis
